tbml/__init__.py
tbml-0.25.dist-info/METADATA
tbml-0.25.dist-info/WHEEL
tbml-0.25.dist-info/top_level.txt
tbml-0.25.dist-info/RECORD
