Metadata-Version: 2.1
Name: tbml
Version: 0.25
Summary: TBML webapp functions
Home-page: https://github.com/kuklachert/tbml_library
Author: Illya Payanov
Author-email: illya.payanov@gmail.com
License: UNKNOWN
Platform: UNKNOWN
